Metadata-Version: 2.1
Name: cookies-anonfiles
Version: 1.4.0
Summary: upload and download to anonfiless server
Home-page: https://github.com/redevil1/anonfiles
Author: CookiesKush42
Author-email: jakbin4747@gmail.com
Project-URL: Bug Tracker, https://github.com/redevil1/anonfiless/issues
Keywords: anonfiles,anonfiles-api,anonfiles-cli,anonymous,upload
Classifier: Programming Language :: Python :: 3.6
Classifier: License :: OSI Approved :: MIT License
Classifier: Natural Language :: English
Classifier: Operating System :: OS Independent
Requires-Python: >=3
License-File: LICENSE
